gdrivedownload.py
gdrivedownload-1.0.1.dist-info/DESCRIPTION.rst
gdrivedownload-1.0.1.dist-info/METADATA
gdrivedownload-1.0.1.dist-info/RECORD
gdrivedownload-1.0.1.dist-info/WHEEL
gdrivedownload-1.0.1.dist-info/entry_points.txt
gdrivedownload-1.0.1.dist-info/metadata.json
gdrivedownload-1.0.1.dist-info/top_level.txt
