Metadata-Version: 2.0
Name: gdrivedownload
Version: 1.0.1
Summary: Simple script that downloads all files from given Google Drive directory
Home-page: https://github.com/m4tx/gdrivedownload
Author: Mateusz Maćkowski
Author-email: m4tx@m4tx.pl
License: MIT
Keywords: google drive api batch download
Platform: UNKNOWN
Classifier: Development Status :: 5 - Production/Stable
Classifier: Environment :: Console
Classifier: Intended Audience :: End Users/Desktop
Classifier: Topic :: Software Development :: Build Tools
Classifier: License :: OSI Approved :: MIT License
Classifier: Natural Language :: English
Classifier: Operating System :: OS Independent
Classifier: Programming Language :: Python :: 3
Classifier: Programming Language :: Python :: 3.2
Classifier: Programming Language :: Python :: 3.3
Classifier: Programming Language :: Python :: 3.4
Classifier: Programming Language :: Python :: 3.5
Classifier: Topic :: Internet :: WWW/HTTP
Classifier: Topic :: Utilities
Requires-Dist: google-api-python-client (>=1.5.0,<2)
